AUTHORS.md
LICENSE.md
README.md
pyproject.toml
setup.cfg
src/model_metadata/__init__.py
src/model_metadata/__main__.py
src/model_metadata/_utils.py
src/model_metadata/_version.py
src/model_metadata/api.py
src/model_metadata/errors.py
src/model_metadata/find.py
src/model_metadata/load.py
src/model_metadata/main.py
src/model_metadata/model_data_files.py
src/model_metadata/model_info.py
src/model_metadata/model_parameter.py
src/model_metadata/model_setup.py
src/model_metadata/modelmetadata.py
src/model_metadata.egg-info/PKG-INFO
src/model_metadata.egg-info/SOURCES.txt
src/model_metadata.egg-info/dependency_links.txt
src/model_metadata.egg-info/entry_points.txt
src/model_metadata.egg-info/requires.txt
src/model_metadata.egg-info/top_level.txt