Metadata-Version: 2.1
Name: model_metadata
Version: 0.8.1
Summary: Model metadata
Author-email: Eric Hutton <huttone@colorado.edu>
Maintainer-email: Eric Hutton <huttone@colorado.edu>
License: MIT
Project-URL: documentation, https://github.com/csdms/model_metadata
Project-URL: homepage, https://github.com/csdms/model_metadata
Project-URL: repository, https://github.com/csdms/model_metadata
Keywords: BMI,Basic Model Interface
Classifier: Development Status :: 4 - Beta
Classifier: Intended Audience :: Science/Research
Classifier: License :: OSI Approved :: MIT License
Classifier: Operating System :: OS Independent
Classifier: Programming Language :: Python :: 3 :: Only
Classifier: Programming Language :: Python :: 3.10
Classifier: Programming Language :: Python :: 3.11
Classifier: Programming Language :: Python :: 3.12
Classifier: Programming Language :: Python :: Implementation :: CPython
Classifier: Topic :: Scientific/Engineering :: Physics
Requires-Python: >=3.10
License-File: LICENSE.md
License-File: AUTHORS.md
Requires-Dist: importlib-resources; python_version < "3.12"
Requires-Dist: jinja2
Requires-Dist: packaging
Requires-Dist: pyyaml
Provides-Extra: dev
Requires-Dist: nox; extra == "dev"
Provides-Extra: testing
Requires-Dist: coveralls; extra == "testing"
Requires-Dist: pytest; extra == "testing"
Requires-Dist: pytest-cov; extra == "testing"
Requires-Dist: pytest-datadir; extra == "testing"
